cloecore/__init__.py
cloecore/py.typed
cloecore/sql_orchestrator/__init__.py
cloecore/sql_orchestrator/batches.py
cloecore/sql_orchestrator/main.py
cloecore/sql_orchestrator/cli/__init__.py
cloecore/sql_orchestrator/cli/gen_sql_orchestrator.py
cloecore/to_airflow/__init__.py
cloecore/to_airflow/main.py
cloecore/to_airflow/templating_engine.py
cloecore/to_airflow/airflow_build/__init__.py
cloecore/to_airflow/airflow_build/dags.py
cloecore/to_airflow/airflow_build/tasks.py
cloecore/to_airflow/cli/__init__.py
cloecore/to_airflow/cli/gen_airflow.py
cloecore/to_airflow/model/__init__.py
cloecore/to_airflow/model/dag.py
cloecore/to_airflow/model/tasks/__init__.py
cloecore/to_airflow/model/tasks/base.py
cloecore/to_airflow/model/tasks/db2fs/__init__.py
cloecore/to_airflow/model/tasks/db2fs/odbc.py
cloecore/to_airflow/model/tasks/exec_sql/__init__.py
cloecore/to_airflow/model/tasks/exec_sql/snowflake.py
cloecore/to_airflow/model/tasks/fs2db/__init__.py
cloecore/to_airflow/model/tasks/fs2db/base.py
cloecore/to_airflow/model/tasks/fs2db/odbc.py
cloecore/to_airflow/model/tasks/fs2db/snowflake.py
cloecore/to_airflow/templates/__init__.py
cloecore/to_airflow/templates/airflow_dag.py.j2
cloecore/to_airflow/templates/task_dbtofs.py.j2
cloecore/to_airflow/templates/task_fstodb.py.j2
cloecore/to_datafactory/__init__.py
cloecore/to_datafactory/azure_resources.py
cloecore/to_datafactory/main.py
cloecore/to_datafactory/Utils/__init__.py
cloecore/to_datafactory/Utils/factory.py
cloecore/to_datafactory/arm/__init__.py
cloecore/to_datafactory/arm/datafactory/__init__.py
cloecore/to_datafactory/arm/datafactory/base.py
cloecore/to_datafactory/arm/datafactory/pipeline_resource.py
cloecore/to_datafactory/arm/datafactory/trigger.py
cloecore/to_datafactory/arm/datafactory/variables.py
cloecore/to_datafactory/arm/datafactory/activities/__init__.py
cloecore/to_datafactory/arm/datafactory/activities/base.py
cloecore/to_datafactory/arm/datafactory/activities/copy_activity.py
CloeCore-20240104.1.dist-info/LICENSE
CloeCore-20240104.1.dist-info/METADATA
CloeCore-20240104.1.dist-info/WHEEL
CloeCore-20240104.1.dist-info/entry_points.txt
CloeCore-20240104.1.dist-info/top_level.txt
CloeCore-20240104.1.dist-info/RECORD
