Metadata-Version: 2.1
Name: CloeCore
Version: 20240104.1
Summary: Core package for CLOE Framework by Initions.
Home-page: https://initions.com/
Author: initions
Author-email: ICSMC_EXT_PYPIORG@accenture.com
License: MIT
Requires-Dist: croniter ==1.3.7
Requires-Dist: jinja2 ==3.1.2
Requires-Dist: click ==8.1.3
Requires-Dist: pydantic ==1.10.2
